astcheck.py
astcheck-0.3.0.dist-info/LICENSE
astcheck-0.3.0.dist-info/WHEEL
astcheck-0.3.0.dist-info/METADATA
astcheck-0.3.0.dist-info/RECORD
