Metadata-Version: 2.1
Name: astcheck
Version: 0.3.0
Summary: Check Python ASTs against templates
Author-email: Thomas Kluyver <thomas@kluyver.me.uk>
Requires-Python: >=3.5
Classifier: Intended Audience :: Developers
Classifier: License :: OSI Approved :: MIT License
Classifier: Programming Language :: Python
Classifier: Programming Language :: Python :: 3
Classifier: Topic :: Software Development :: Code Generators
Classifier: Topic :: Software Development :: Testing
Project-URL: Source, https://github.com/takluyver/astcheck
